src/GlobalOptimizationDNLA/Algorithm.py
src/GlobalOptimizationDNLA/PostProcessor.py
src/GlobalOptimizationDNLA/__init__.py
tests/Rastrigin100000.py
tests/Rastrigin14000.py
tests/Rastrigin14000SimAnn.py
GlobalOptimization_DNLA-0.0.1.dist-info/LICENCE
GlobalOptimization_DNLA-0.0.1.dist-info/METADATA
GlobalOptimization_DNLA-0.0.1.dist-info/WHEEL
GlobalOptimization_DNLA-0.0.1.dist-info/top_level.txt
GlobalOptimization_DNLA-0.0.1.dist-info/RECORD
